climenu/__init__.py
easyclimenu-0.1.0.dist-info/licenses/LICENSE
easyclimenu-0.1.0.dist-info/METADATA
easyclimenu-0.1.0.dist-info/WHEEL
easyclimenu-0.1.0.dist-info/top_level.txt
easyclimenu-0.1.0.dist-info/RECORD
