Metadata-Version: 2.4
Name: EasyCliMenu
Version: 0.1.0
Summary: Simple CLI menu library for Python
Author: Bowser-2077
Author-email: hostinfire@gmail.com
Classifier: Programming Language :: Python :: 3
Classifier: Operating System :: OS Independent
Classifier: Topic :: Utilities
Requires-Python: >=3.6
License-File: LICENSE
Dynamic: author
Dynamic: author-email
Dynamic: classifier
Dynamic: description
Dynamic: description-content-type
Dynamic: license-file
Dynamic: requires-python
Dynamic: summary
